zmeiapi/__init__.py
zmeiapi/abstract_factories/MaterialCreators.py
zmeiapi/abstract_factories/PinCreators.py
zmeiapi/abstract_factories/__init__.py
zmeiapi/data/Materials.py
zmeiapi/data/Parameters.py
zmeiapi/data/__init__.py
zmeiapi/data/materials_data.yml
zmeiapi/data/nuclides_dict.pkl
zmeiapi/data/nuclides_masses.pkl
zmeiapi/data/res_keys.yml
zmeiapi/factories/__init__.py
zmeiapi/objects/BurnupInput.py
zmeiapi/objects/Cell.py
zmeiapi/objects/General.py
zmeiapi/objects/Lattice.py
zmeiapi/objects/Material.py
zmeiapi/objects/Pin.py
zmeiapi/objects/Res.py
zmeiapi/objects/Surface.py
zmeiapi/objects/__init__.py
zmeiapi/readers/BumatReader.py
zmeiapi/readers/SerpentOut.py
zmeiapi/readers/__init__.py
zmeiapi/utilities/Burnup.py
zmeiapi/utilities/Concentrations.py
zmeiapi/utilities/Graphs.py
zmeiapi/utilities/__init__.py
zmeiapi/utilities/hex.py
zmeiapi/zmei_io/Logger.py
zmeiapi/zmei_io/__init__.py
zmeiapi-0.1.30.2024.dist-info/LICENSE.txt
zmeiapi-0.1.30.2024.dist-info/METADATA
zmeiapi-0.1.30.2024.dist-info/WHEEL
zmeiapi-0.1.30.2024.dist-info/top_level.txt
zmeiapi-0.1.30.2024.dist-info/RECORD
