Metadata-Version: 2.1
Name: zmeiapi
Version: 0.1.30.2024
Summary: Useful tools to work with Zmei calculation code
Home-page: https://github.com/vliromanenko/zmei-api
Download-URL: https://pypi.org/project/zmeiapi/
Author: Vladislav Romanenko
Author-email: vliromanenko@yandex.ru
License: MIT
Keywords: zmei-api
License-File: LICENSE.txt
